{
  "guid": "53b3d99d1c8fc0d46a05493137c6fcf9",
  "file_path": "D:\\Bug_injection_project\\HandPosing_Demo-master\\Assets\\Oculus\\VR\\Plugins\\1.55.0\\Win\\OVRPlugin.dll.meta",
  "name": "OVRPlugin.dll",
  "type": "meta",
  "file_size": 752,
  "num_components": 0,
  "COMPONENTS": [
    {
      "id": "PluginImporter",
      "PluginImporter": [
        {
          "externalObjects": ""
        },
        {
          "serializedVersion": "2"
        },
        {
          "iconMap": ""
        },
        {
          "executionOrder": ""
        },
        {
          "defineConstraints": "[]"
        },
        {
          "isPreloaded": "0"
        },
        {
          "isOverridable": "0"
        },
        {
          "isExplicitlyReferenced": "0"
        },
        {
          "validateReferences": "1"
        },
        {
          "platformData": [
            {
              "- first": [
                {
                  "": "Editor"
                }
              ]
            },
            {
              "second": [
                {
                  "enabled": "0"
                },
                {
                  "settings": [
                    {
                      "CPU": "X86"
                    },
                    {
                      "OS": "Windows"
                    }
                  ]
                }
              ]
            },
            {
              "- first": [
                {
                  "Any": ""
                }
              ]
            },
            {
              "second": [
                {
                  "enabled": "0"
                },
                {
                  "settings": ""
                }
              ]
            },
            {
              "- first": [
                {
                  "Editor": "Editor"
                }
              ]
            },
            {
              "second": [
                {
                  "enabled": "1"
                },
                {
                  "settings": [
                    {
                      "CPU": "X86"
                    },
                    {
                      "DefaultValueInitialized": "true"
                    },
                    {
                      "OS": "Windows"
                    }
                  ]
                }
              ]
            },
            {
              "- first": [
                {
                  "Standalone": "Win"
                }
              ]
            },
            {
              "second": [
                {
                  "enabled": "1"
                },
                {
                  "settings": ""
                }
              ]
            }
          ]
        },
        {
          "userData": ""
        },
        {
          "assetBundleName": ""
        },
        {
          "assetBundleVariant": ""
        }
      ]
    }
  ],
  "ProjectName": "Oculus",
  "ProjectPath": "D:\\Bug_injection_project\\HandPosing_Demo-master\\Assets\\Oculus"
}