{
  "guid": "8de0f603bcd864c41a6fbf4c1788ef9c",
  "file_path": "D:\\Bug_injection_project\\HandPosing_Demo-master\\Assets\\Oculus\\SampleFramework\\Usage\\Locomotion\\Shaders\\TriPlanarWorld.shader.meta",
  "name": "TriPlanarWorld.shader",
  "type": "meta",
  "file_size": 197,
  "num_components": 0,
  "COMPONENTS": [
    {
      "id": "ShaderImporter",
      "ShaderImporter": [
        {
          "defaultTextures": "[]"
        },
        {
          "userData": ""
        },
        {
          "assetBundleName": ""
        },
        {
          "assetBundleVariant": ""
        }
      ]
    }
  ],
  "ProjectName": "Oculus",
  "ProjectPath": "D:\\Bug_injection_project\\HandPosing_Demo-master\\Assets\\Oculus"
}