{
  "guid": "e2c4ef7503877e647b22a4089384f04f",
  "file_path": "D:\\Bug_injection_project\\HandPosing_Demo-master\\Assets\\Oculus\\Avatar\\Content\\Prefabs.meta",
  "name": "Prefabs",
  "type": "meta",
  "file_size": 193,
  "num_components": 0,
  "COMPONENTS": [
    {
      "id": "DefaultImporter",
      "DefaultImporter": [
        {
          "userData": ""
        },
        {
          "assetBundleName": ""
        },
        {
          "assetBundleVariant": ""
        }
      ]
    }
  ],
  "ProjectName": "Oculus",
  "ProjectPath": "D:\\Bug_injection_project\\HandPosing_Demo-master\\Assets\\Oculus"
}