{
  "guid": "f6d58d9d4ff0e8f4ca5f73c5ec106551",
  "file_path": "D:\\Bug_injection_project\\HandPosing_Demo-master\\Assets\\Oculus\\VR\\Editor\\OVRPlatformTool.cs.meta",
  "name": "OVRPlatformTool.cs",
  "type": "meta",
  "file_size": 286,
  "num_components": 0,
  "COMPONENTS": [
    {
      "id": "MonoImporter",
      "MonoImporter": [
        {
          "externalObjects": ""
        },
        {
          "serializedVersion": "2"
        },
        {
          "defaultReferences": "[]"
        },
        {
          "executionOrder": "0"
        },
        {
          "icon": [
            {
              "instanceID": "0"
            }
          ]
        },
        {
          "userData": ""
        },
        {
          "assetBundleName": ""
        },
        {
          "assetBundleVariant": ""
        }
      ]
    }
  ],
  "ProjectName": "Oculus",
  "ProjectPath": "D:\\Bug_injection_project\\HandPosing_Demo-master\\Assets\\Oculus"
}