{
  "guid": "354a5d3fc93892c44978423fd55d7196",
  "file_path": "D:\\Bug_injection_project\\HandPosing_Demo-master\\Assets\\Oculus\\SampleFramework\\Usage\\OVROverlay\\Materials\\Tile_Mat_Cinema.mat",
  "name": "Tile_Mat_Cinema",
  "type": "mat",
  "file_size": 941,
  "num_components": 1,
  "COMPONENTS": [
    {
      "id": "2100000",
      "Material": [
        {
          "serializedVersion": "6"
        },
        {
          "m_ObjectHideFlags": "0"
        },
        {
          "m_PrefabParentObject": [
            {
              "fileID": "0"
            }
          ]
        },
        {
          "m_PrefabInternal": [
            {
              "fileID": "0"
            }
          ]
        },
        {
          "m_Name": "Tile_Mat_Cinema"
        },
        {
          "m_Shader": [
            {
              "fileID": "10751"
            },
            {
              "guid": "0000000000000000f000000000000000"
            },
            {
              "type": "0"
            }
          ]
        },
        {
          "m_ShaderKeywords": ""
        },
        {
          "m_LightmapFlags": "5"
        },
        {
          "m_EnableInstancingVariants": "0"
        },
        {
          "m_DoubleSidedGI": "0"
        },
        {
          "m_CustomRenderQueue": "-1"
        },
        {
          "stringTagMap": ""
        },
        {
          "disabledShaderPasses": "[]"
        },
        {
          "m_SavedProperties": [
            {
              "serializedVersion": "3"
            },
            {
              "m_TexEnvs": [
                {
                  "- _MainTex": [
                    {
                      "m_Texture": [
                        {
                          "fileID": "2800000"
                        },
                        {
                          "guid": "bbb53525b0a17364d8b239d5627667e5"
                        },
                        {
                          "type": "3"
                        }
                      ]
                    },
                    {
                      "m_Scale": [
                        {
                          "x": "1"
                        },
                        {
                          "y": "1"
                        }
                      ]
                    },
                    {
                      "m_Offset": [
                        {
                          "x": "0"
                        },
                        {
                          "y": "0"
                        }
                      ]
                    }
                  ]
                }
              ]
            },
            {
              "m_Floats": [
                {
                  " _Cutoff": "0.5"
                },
                {
                  " _InvFade": "0.39"
                },
                {
                  " _Shininess": "0.1"
                }
              ]
            },
            {
              "m_Colors": [
                {
                  "- _Color": [
                    {
                      "r": "1"
                    },
                    {
                      "g": "1"
                    },
                    {
                      "b": "1"
                    },
                    {
                      "a": "1"
                    }
                  ]
                },
                {
                  "- _Emission": [
                    {
                      "r": "0"
                    },
                    {
                      "g": "0"
                    },
                    {
                      "b": "0"
                    },
                    {
                      "a": "0"
                    }
                  ]
                },
                {
                  "- _SpecColor": [
                    {
                      "r": "0"
                    },
                    {
                      "g": "0"
                    },
                    {
                      "b": "0"
                    },
                    {
                      "a": "0"
                    }
                  ]
                },
                {
                  "- _TintColor": [
                    {
                      "r": "1"
                    },
                    {
                      "g": "0.984"
                    },
                    {
                      "b": "1"
                    },
                    {
                      "a": "0.5"
                    }
                  ]
                }
              ]
            }
          ]
        }
      ]
    }
  ],
  "ProjectName": "Oculus",
  "ProjectPath": "D:\\Bug_injection_project\\HandPosing_Demo-master\\Assets\\Oculus"
}